{
  "name": "Milton Palmer",
  "age": 29,
  "address": {
    "street": "Ehosaf Pike",
    "city": "Zumcomeg",
    "state": "NE",
    "zip": "25365"
  },
  "contact": {
    "phone": "(305) 311-4494",
    "servicePhone": "800252744"
  },
  "birthday": "1967-06-01T21:01:31.613Z",
  "ip": "21.44.180.184",
  "foo": "bar",
  "profile": {
    "about": "Lu uba donehdo vag ret zupuka nufsugabe libis go apsik ruso domji. Se zup cebjum fipbev ahavi hiwke het agupan dipmik za ituub foloz pekdupi funso olhig cevame rusgoddi wek. Ziihoic emraw gu ab lukbisu vuv sedetev zajosmav huzabjir nevwig bamrovaho kovwevaz beleit.",
    "bio": "Ecoanvig obrot zot fi naver sokdewen hel ka bilidven im dinimlol ra gelu zojojoj. Dup je atamib diz bes hoh jofgo fonunji obguh depmeuha jasmij liive jagdakfus pit makgosizu davobbih uvalabul ro. Mabganle zowi nena zadwouk camofsu naozi eze wib kanuri kuhitiz acorovap ijo usa kuwpu ziot unkecli ruwog. Libidriw ri saju betoeg tohriug navir cunwu da suj ce zij tepjomwin bu nuujumuz."
  },
  "apiKey": "58515653229f4f63999155aceec17de84be6dea7aa74f5ea31614ab7dafa3d24",
  "currency": {
    "code": "AZN",
    "name": "Azerbaijan New Manat"
  }
}