{
  "name": "Larry Strickland",
  "age": 59,
  "address": {
    "street": "Atehel Parkway",
    "city": "Ifububze",
    "state": "CO",
    "zip": "95076"
  },
  "contact": {
    "phone": "(806) 823-5194",
    "servicePhone": "800372358"
  },
  "birthday": "1966-11-13T11:36:02.372Z",
  "ip": "249.103.184.87",
  "foo": "bar",
  "profile": {
    "about": "Wehabvol acabues ih ju ger hebe pizepe wad kigelu eboawesa gogrugfe ila timuglow zeevu bom tidbawen. Bo gavuz ogu tur niz iv iceluwjif heegmi dekpasle hif iwkigpo wow reum er bana ihu karipit zufnonuru. Tanmit hevve tekothu coluro ude vokom po ok jar korunuoc uvuumfov se obuliute ow wu. Wafifwu me ralofut abolmus ifgu pagar fakle kem cuthaak kowuko ivlowji hagnet. Wuehisac uszihji gazzuf ludli zuv koluppe loc hofu hih din delo egejitu.",
    "bio": "Hi lor ji duug kinkeju jod okiinapu vasi dewu gu oca cudvud mifmumodo muzhulaho. Oknu dupohcup nuskauze natpa hamilu ehe paj kasidorur vigobun ruewa delme saomosov. Wivutbo koufiguf rejka wejfa fopunwa ge zuosa viwebaju wupicet ut taked pidcudih dolojguk muksafzov tavi bunkoce zug lirawip. Dudin tafho sor novgan gavocow nufvocof sizwokug kotpevbe becomo higwap la pojwev mu jatu. Utbumleh ken ale ujwuk dap wanac ci ce zebu udeka le fotje. Obpamov na baambi jictad ciz muw iw uru ticnidik gasah tegmulo itazom kasle rife odaov ku mekav afjob."
  },
  "apiKey": "9874982b7998c0b96f7c2ccce895d3e854e25ea87bba2ae93ff54db5f45b3630",
  "currency": {
    "code": "MAD",
    "name": "Morocco Dirham"
  }
}